sgt/__init__.py
sgt/core.py
sgt/crystal.py
sgt/hdf5image.py
sgt/legacy_geometry.py
sgt/npzimage.py
sgt/pilatus.py
scattering_geometry_tools-1.0.0.dist-info/METADATA
scattering_geometry_tools-1.0.0.dist-info/WHEEL
scattering_geometry_tools-1.0.0.dist-info/licenses/LICENSE
scattering_geometry_tools-1.0.0.dist-info/RECORD
