Metadata-Version: 2.4
Name: scattering-geometry-tools
Version: 1.0.0
Summary: Tools for calculations of geometries in scattering experiments. 
Project-URL: Homepage, https://github.com/shntrnkgw/scattering-geometry-tools
Author-email: Shintaro Nakagawa <shntrnkgw@gmail.com>
License: MIT License
License-File: LICENSE
Classifier: License :: OSI Approved :: MIT License
Classifier: Programming Language :: Python :: 3.13
Requires-Python: >=3.13
Requires-Dist: h5py>=3.13.0
Requires-Dist: numpy>=2.2.3
